[
	{
		"name": "Aerith Theme FFVII  (Cloudy-Sky)",
		"bpm": 200,
		"bitsPerPage": 16,
		"pitchLevel": 3,
		"isComposed": false,
		"songNotes": [
			{
				"time": 1228,
				"key": "1Key2"
			},
			{
				"time": 1236,
				"key": "1Key0"
			},
			{
				"time": 1654,
				"key": "1Key4"
			},
			{
				"time": 2077,
				"key": "1Key7"
			},
			{
				"time": 4258,
				"key": "1Key6"
			},
			{
				"time": 4267,
				"key": "1Key4"
			},
			{
				"time": 4659,
				"key": "1Key4"
			},
			{
				"time": 5069,
				"key": "1Key1"
			},
			{
				"time": 7062,
				"key": "1Key2"
			},
			{
				"time": 7070,
				"key": "1Key0"
			},
			{
				"time": 7444,
				"key": "1Key4"
			},
			{
				"time": 7850,
				"key": "1Key7"
			},
			{
				"time": 8270,
				"key": "1Key6"
			},
			{
				"time": 8645,
				"key": "1Key6"
			},
			{
				"time": 8653,
				"key": "1Key8"
			},
			{
				"time": 9036,
				"key": "1Key7"
			},
			{
				"time": 9398,
				"key": "1Key5"
			},
			{
				"time": 9821,
				"key": "1Key6"
			},
			{
				"time": 10201,
				"key": "1Key1"
			},
			{
				"time": 10212,
				"key": "1Key4"
			},
			{
				"time": 11622,
				"key": "1Key1"
			},
			{
				"time": 13046,
				"key": "1Key7"
			},
			{
				"time": 13057,
				"key": "1Key9"
			},
			{
				"time": 13466,
				"key": "1Key11"
			},
			{
				"time": 13855,
				"key": "1Key9"
			},
			{
				"time": 13878,
				"key": "1Key14"
			},
			{
				"time": 14624,
				"key": "1Key8"
			},
			{
				"time": 15393,
				"key": "1Key7"
			},
			{
				"time": 16141,
				"key": "1Key13"
			},
			{
				"time": 16156,
				"key": "1Key11"
			},
			{
				"time": 16549,
				"key": "1Key11"
			},
			{
				"time": 16893,
				"key": "1Key6"
			},
			{
				"time": 16902,
				"key": "1Key8"
			},
			{
				"time": 17709,
				"key": "1Key5"
			},
			{
				"time": 18418,
				"key": "1Key4"
			},
			{
				"time": 18939,
				"key": "1Key7"
			},
			{
				"time": 18950,
				"key": "1Key3"
			},
			{
				"time": 19135,
				"key": "1Key8"
			},
			{
				"time": 19334,
				"key": "1Key7"
			},
			{
				"time": 21450,
				"key": "1Key9"
			},
			{
				"time": 21459,
				"key": "1Key7"
			},
			{
				"time": 21821,
				"key": "1Key8"
			},
			{
				"time": 22198,
				"key": "1Key7"
			},
			{
				"time": 22597,
				"key": "1Key8"
			},
			{
				"time": 22957,
				"key": "1Key3"
			},
			{
				"time": 22963,
				"key": "1Key7"
			},
			{
				"time": 23691,
				"key": "1Key0"
			},
			{
				"time": 24083,
				"key": "1Key2"
			},
			{
				"time": 24478,
				"key": "1Key4"
			},
			{
				"time": 24823,
				"key": "1Key7"
			},
			{
				"time": 25628,
				"key": "1Key9"
			},
			{
				"time": 26002,
				"key": "1Key11"
			},
			{
				"time": 27696,
				"key": "1Key7"
			},
			{
				"time": 28053,
				"key": "1Key8"
			},
			{
				"time": 28400,
				"key": "1Key7"
			},
			{
				"time": 28415,
				"key": "1Key9"
			},
			{
				"time": 28420,
				"key": "1Key5"
			},
			{
				"time": 29091,
				"key": "1Key2"
			},
			{
				"time": 29467,
				"key": "1Key4"
			},
			{
				"time": 29862,
				"key": "1Key7"
			},
			{
				"time": 30592,
				"key": "1Key9"
			},
			{
				"time": 30949,
				"key": "1Key10"
			},
			{
				"time": 31322,
				"key": "1Key9"
			},
			{
				"time": 31329,
				"key": "1Key6"
			},
			{
				"time": 31336,
				"key": "1Key11"
			},
			{
				"time": 32028,
				"key": "1Key2"
			},
			{
				"time": 32389,
				"key": "1Key4"
			},
			{
				"time": 32747,
				"key": "1Key6"
			},
			{
				"time": 33439,
				"key": "1Key12"
			},
			{
				"time": 33816,
				"key": "1Key13"
			},
			{
				"time": 34156,
				"key": "1Key12"
			},
			{
				"time": 34165,
				"key": "1Key14"
			},
			{
				"time": 34828,
				"key": "1Key12"
			},
			{
				"time": 35444,
				"key": "1Key3"
			},
			{
				"time": 35463,
				"key": "1Key0"
			},
			{
				"time": 36119,
				"key": "1Key10"
			},
			{
				"time": 36695,
				"key": "1Key11"
			},
			{
				"time": 36706,
				"key": "1Key7"
			},
			{
				"time": 36891,
				"key": "1Key12"
			},
			{
				"time": 37079,
				"key": "1Key11"
			},
			{
				"time": 37431,
				"key": "1Key0"
			},
			{
				"time": 37780,
				"key": "1Key2"
			},
			{
				"time": 38111,
				"key": "1Key4"
			},
			{
				"time": 38761,
				"key": "1Key11"
			},
			{
				"time": 39107,
				"key": "1Key9"
			},
			{
				"time": 39466,
				"key": "1Key4"
			},
			{
				"time": 39477,
				"key": "1Key2"
			},
			{
				"time": 39485,
				"key": "1Key6"
			},
			{
				"time": 40180,
				"key": "1Key2"
			},
			{
				"time": 40864,
				"key": "1Key4"
			},
			{
				"time": 41538,
				"key": "1Key6"
			},
			{
				"time": 42160,
				"key": "1Key2"
			},
			{
				"time": 42172,
				"key": "1Key5"
			},
			{
				"time": 43677,
				"key": "1Key4"
			},
			{
				"time": 43687,
				"key": "1Key2"
			},
			{
				"time": 44634,
				"key": "1Key12"
			},
			{
				"time": 44965,
				"key": "1Key11"
			},
			{
				"time": 45315,
				"key": "1Key7"
			},
			{
				"time": 45324,
				"key": "1Key3"
			},
			{
				"time": 45329,
				"key": "1Key5"
			},
			{
				"time": 46019,
				"key": "1Key0"
			},
			{
				"time": 46670,
				"key": "1Key3"
			},
			{
				"time": 47307,
				"key": "1Key5"
			},
			{
				"time": 47954,
				"key": "1Key2"
			},
			{
				"time": 47963,
				"key": "1Key4"
			},
			{
				"time": 49470,
				"key": "1Key3"
			},
			{
				"time": 49479,
				"key": "1Key1"
			},
			{
				"time": 50077,
				"key": "1Key11"
			},
			{
				"time": 50396,
				"key": "1Key9"
			},
			{
				"time": 50728,
				"key": "1Key4"
			},
			{
				"time": 50744,
				"key": "1Key2"
			},
			{
				"time": 50751,
				"key": "1Key6"
			},
			{
				"time": 51381,
				"key": "1Key2"
			},
			{
				"time": 52018,
				"key": "1Key4"
			},
			{
				"time": 52683,
				"key": "1Key6"
			},
			{
				"time": 53302,
				"key": "1Key2"
			},
			{
				"time": 53310,
				"key": "1Key5"
			},
			{
				"time": 54559,
				"key": "1Key2"
			},
			{
				"time": 54568,
				"key": "1Key4"
			},
			{
				"time": 55140,
				"key": "1Key12"
			},
			{
				"time": 55450,
				"key": "1Key13"
			},
			{
				"time": 55741,
				"key": "1Key14"
			},
			{
				"time": 55750,
				"key": "1Key12"
			},
			{
				"time": 56512,
				"key": "1Key0"
			},
			{
				"time": 57102,
				"key": "1Key3"
			},
			{
				"time": 57700,
				"key": "1Key5"
			},
			{
				"time": 58298,
				"key": "1Key7"
			},
			{
				"time": 58311,
				"key": "1Key3"
			},
			{
				"time": 58316,
				"key": "1Key5"
			},
			{
				"time": 58909,
				"key": "1Key14"
			},
			{
				"time": 59498,
				"key": "1Key9"
			},
			{
				"time": 59507,
				"key": "1Key13"
			},
			{
				"time": 59532,
				"key": "1Key11"
			},
			{
				"time": 60169,
				"key": "1Key12"
			},
			{
				"time": 60853,
				"key": "1Key9"
			},
			{
				"time": 60863,
				"key": "1Key7"
			},
			{
				"time": 60868,
				"key": "1Key11"
			},
			{
				"time": 61915,
				"key": "1Key7"
			},
			{
				"time": 61922,
				"key": "1Key9"
			},
			{
				"time": 62834,
				"key": "1Key0"
			},
			{
				"time": 63109,
				"key": "1Key3"
			},
			{
				"time": 63453,
				"key": "1Key3"
			},
			{
				"time": 63460,
				"key": "1Key7"
			},
			{
				"time": 63466,
				"key": "1Key5"
			},
			{
				"time": 64057,
				"key": "1Key14"
			},
			{
				"time": 64643,
				"key": "1Key13"
			},
			{
				"time": 64653,
				"key": "1Key9"
			},
			{
				"time": 64664,
				"key": "1Key11"
			},
			{
				"time": 65288,
				"key": "1Key12"
			},
			{
				"time": 65890,
				"key": "1Key13"
			},
			{
				"time": 65897,
				"key": "1Key9"
			},
			{
				"time": 65905,
				"key": "1Key11"
			},
			{
				"time": 66825,
				"key": "1Key9"
			},
			{
				"time": 67159,
				"key": "1Key9"
			},
			{
				"time": 67169,
				"key": "1Key4"
			},
			{
				"time": 67176,
				"key": "1Key6"
			},
			{
				"time": 67781,
				"key": "1Key6"
			},
			{
				"time": 68360,
				"key": "1Key2"
			},
			{
				"time": 68371,
				"key": "1Key5"
			},
			{
				"time": 68390,
				"key": "1Key0"
			},
			{
				"time": 68971,
				"key": "1Key14"
			},
			{
				"time": 69558,
				"key": "1Key13"
			},
			{
				"time": 69570,
				"key": "1Key9"
			},
			{
				"time": 69577,
				"key": "1Key11"
			},
			{
				"time": 70191,
				"key": "1Key12"
			},
			{
				"time": 70738,
				"key": "1Key8"
			},
			{
				"time": 70752,
				"key": "1Key11"
			},
			{
				"time": 70771,
				"key": "1Key6"
			},
			{
				"time": 71689,
				"key": "1Key8"
			},
			{
				"time": 71698,
				"key": "1Key6"
			},
			{
				"time": 72769,
				"key": "1Key8"
			},
			{
				"time": 72985,
				"key": "1Key9"
			},
			{
				"time": 73190,
				"key": "1Key8"
			},
			{
				"time": 73210,
				"key": "1Key5"
			},
			{
				"time": 73213,
				"key": "1Key10"
			},
			{
				"time": 73565,
				"key": "1Key9"
			},
			{
				"time": 73892,
				"key": "1Key8"
			},
			{
				"time": 74260,
				"key": "1Key7"
			},
			{
				"time": 75688,
				"key": "1Key3"
			},
			{
				"time": 75694,
				"key": "1Key0"
			},
			{
				"time": 77112,
				"key": "1Key7"
			},
			{
				"time": 77126,
				"key": "1Key5"
			},
			{
				"time": 77134,
				"key": "1Key10"
			},
			{
				"time": 77480,
				"key": "1Key9"
			},
			{
				"time": 77852,
				"key": "1Key7"
			},
			{
				"time": 78215,
				"key": "1Key8"
			},
			{
				"time": 78595,
				"key": "1Key4"
			},
			{
				"time": 78602,
				"key": "1Key7"
			},
			{
				"time": 78609,
				"key": "1Key2"
			},
			{
				"time": 79363,
				"key": "1Key0"
			},
			{
				"time": 80077,
				"key": "1Key2"
			},
			{
				"time": 80827,
				"key": "1Key4"
			},
			{
				"time": 81731,
				"key": "1Key4"
			},
			{
				"time": 81741,
				"key": "1Key2"
			},
			{
				"time": 81749,
				"key": "1Key7"
			},
			{
				"time": 81755,
				"key": "1Key0"
			}
		]
	}
]